graphrails/__init__.py
graphrails/skeleton.py
graphrails-0.0.0.dist-info/LICENSE.txt
graphrails-0.0.0.dist-info/METADATA
graphrails-0.0.0.dist-info/WHEEL
graphrails-0.0.0.dist-info/top_level.txt
graphrails-0.0.0.dist-info/RECORD
