Metadata-Version: 2.1
Name: graphrails
Version: 0.0.0
Summary: To add graph based rails to the LLMs
Home-page: https://github.com/pyscaffold/pyscaffold/
Author: Jaya Prakash
Author-email: jp@smartbots.ai
License: MIT
Project-URL: Documentation, https://pyscaffold.org/
Platform: any
Classifier: Development Status :: 4 - Beta
Classifier: Programming Language :: Python
Requires-Dist: importlib-metadata ; python_version < "3.8"
Provides-Extra: testing
Requires-Dist: setuptools ; extra == 'testing'
Requires-Dist: pytest ; extra == 'testing'
Requires-Dist: pytest-cov ; extra == 'testing'
